anomalywatchdog/__init__.py
anomalywatchdog/anomaly_features/CalendarFeatureCreator.py
anomalywatchdog/anomaly_features/__init__.py
anomalywatchdog/anomaly_features/create_features.py
anomalywatchdog/config_ad.yaml
anomalywatchdog/core.py
anomalywatchdog/data_treatment/__init__.py
anomalywatchdog/data_treatment/data_handler.py
anomalywatchdog/data_treatment/input_checker.py
anomalywatchdog/data_treatment/model_updater.py
anomalywatchdog/engine/__init__.py
anomalywatchdog/engine/model_factory.py
anomalywatchdog/engine/model_predictor.py
anomalywatchdog/engine/model_trainer.py
anomalywatchdog/modelling/__init__.py
anomalywatchdog/modelling/abstract_model.py
anomalywatchdog/modelling/auto_arima_model.py
anomalywatchdog/modelling/autoencoder_conv_model.py
anomalywatchdog/modelling/autoencoder_lstm_model.py
anomalywatchdog/modelling/prophet_model.py
anomalywatchdog/utils/__init__.py
anomalywatchdog/utils/create_fourier_terms.py
anomalywatchdog/utils/create_sequences.py
anomalywatchdog/utils/data_normalizer.py
anomalywatchdog/utils/kruskal_test_seasonality.py
anomalywatchdog-0.0.7.dist-info/METADATA
anomalywatchdog-0.0.7.dist-info/WHEEL
anomalywatchdog-0.0.7.dist-info/RECORD
