Metadata-Version: 2.3
Name: anomalywatchdog
Version: 0.0.7
Summary: 
License: MIT
Author: alexis-vazquez
Author-email: alexis.vazquez@adevinta.com
Requires-Python: >=3.9,<4.0
Classifier: License :: OSI Approved :: MIT License
Classifier: Programming Language :: Python :: 3
Classifier: Programming Language :: Python :: 3.9
Classifier: Programming Language :: Python :: 3.10
Classifier: Programming Language :: Python :: 3.11
Classifier: Programming Language :: Python :: 3.12
Classifier: Programming Language :: Python :: 3.13
Requires-Dist: PyYAML (>=6.0,<7.0)
Requires-Dist: holidays (>=0.50,<0.51)
Requires-Dist: pandas (==1.5.2)
Requires-Dist: pmdarima (>=2.0.4,<3.0.0)
Requires-Dist: prophet (>=1.1.5,<2.0.0)
Requires-Dist: pyspark (==3.2.1)
Requires-Dist: scikit-learn (>=1.4.2,<2.0.0)
Requires-Dist: spicy (>=0.16.0,<0.17.0)
Requires-Dist: tensorflow (>=2.16.1,<3.0.0)
Requires-Dist: wheel (>=0.43.0,<0.44.0)
